pyslfp/__init__.py
pyslfp/config.py
pyslfp/data/ice5g/ice5g_v1.2_00.0k_1deg.nc
pyslfp/data/ice5g/ice5g_v1.2_00.5k_1deg.nc
pyslfp/data/ice5g/ice5g_v1.2_01.0k_1deg.nc
pyslfp/data/ice5g/ice5g_v1.2_01.5k_1deg.nc
pyslfp/data/ice5g/ice5g_v1.2_02.0k_1deg.nc
pyslfp/data/ice5g/ice5g_v1.2_02.5k_1deg.nc
pyslfp/data/ice5g/ice5g_v1.2_03.0k_1deg.nc
pyslfp/data/ice5g/ice5g_v1.2_03.5k_1deg.nc
pyslfp/data/ice5g/ice5g_v1.2_04.0k_1deg.nc
pyslfp/data/ice5g/ice5g_v1.2_04.5k_1deg.nc
pyslfp/data/ice5g/ice5g_v1.2_05.0k_1deg.nc
pyslfp/data/ice5g/ice5g_v1.2_05.5k_1deg.nc
pyslfp/data/ice5g/ice5g_v1.2_06.0k_1deg.nc
pyslfp/data/ice5g/ice5g_v1.2_06.5k_1deg.nc
pyslfp/data/ice5g/ice5g_v1.2_07.0k_1deg.nc
pyslfp/data/ice5g/ice5g_v1.2_07.5k_1deg.nc
pyslfp/data/ice5g/ice5g_v1.2_08.0k_1deg.nc
pyslfp/data/ice5g/ice5g_v1.2_08.5k_1deg.nc
pyslfp/data/ice5g/ice5g_v1.2_09.0k_1deg.nc
pyslfp/data/ice5g/ice5g_v1.2_09.5k_1deg.nc
pyslfp/data/ice5g/ice5g_v1.2_10.0k_1deg.nc
pyslfp/data/ice5g/ice5g_v1.2_10.5k_1deg.nc
pyslfp/data/ice5g/ice5g_v1.2_11.0k_1deg.nc
pyslfp/data/ice5g/ice5g_v1.2_11.5k_1deg.nc
pyslfp/data/ice5g/ice5g_v1.2_12.0k_1deg.nc
pyslfp/data/ice5g/ice5g_v1.2_12.5k_1deg.nc
pyslfp/data/ice5g/ice5g_v1.2_13.0k_1deg.nc
pyslfp/data/ice5g/ice5g_v1.2_13.5k_1deg.nc
pyslfp/data/ice5g/ice5g_v1.2_14.0k_1deg.nc
pyslfp/data/ice5g/ice5g_v1.2_14.5k_1deg.nc
pyslfp/data/ice5g/ice5g_v1.2_15.0k_1deg.nc
pyslfp/data/ice5g/ice5g_v1.2_15.5k_1deg.nc
pyslfp/data/ice5g/ice5g_v1.2_16.0k_1deg.nc
pyslfp/data/ice5g/ice5g_v1.2_16.5k_1deg.nc
pyslfp/data/ice5g/ice5g_v1.2_17.0k_1deg.nc
pyslfp/data/ice5g/ice5g_v1.2_18.0k_1deg.nc
pyslfp/data/ice5g/ice5g_v1.2_19.0k_1deg.nc
pyslfp/data/ice5g/ice5g_v1.2_20.0k_1deg.nc
pyslfp/data/ice5g/ice5g_v1.2_21.0k_1deg.nc
pyslfp/data/ice6g/I6_C.VM5a_1deg.0.5.nc
pyslfp/data/ice6g/I6_C.VM5a_1deg.0.nc
pyslfp/data/ice6g/I6_C.VM5a_1deg.1.5.nc
pyslfp/data/ice6g/I6_C.VM5a_1deg.1.nc
pyslfp/data/ice6g/I6_C.VM5a_1deg.10.5.nc
pyslfp/data/ice6g/I6_C.VM5a_1deg.10.nc
pyslfp/data/ice6g/I6_C.VM5a_1deg.11.5.nc
pyslfp-1.1.4.dist-info/METADATA
pyslfp-1.1.4.dist-info/WHEEL
pyslfp-1.1.4.dist-info/licenses/LICENSE
pyslfp-1.1.4.dist-info/RECORD
