Metadata-Version: 2.4
Name: pyslfp
Version: 1.1.4
Summary: Package for computing elastic sea level fingerprints
License: BSD-3-Clause
License-File: LICENSE
Author: David Al-Attar and Dan Heathcote
Requires-Python: >=3.11
Classifier: License :: OSI Approved :: BSD License
Classifier: Programming Language :: Python :: 3
Classifier: Programming Language :: Python :: 3.11
Classifier: Programming Language :: Python :: 3.12
Classifier: Programming Language :: Python :: 3.13
Classifier: Programming Language :: Python :: 3.14
Requires-Dist: Cartopy (>=0.23.0,<0.24.0)
Requires-Dist: cf-xarray (>=0.10.9,<0.11.0)
Requires-Dist: matplotlib (>=3.0.0)
Requires-Dist: numpy (>=1.26.0)
Requires-Dist: pygeoinf (>=1.3.8)
Requires-Dist: pyqt6 (>=6.0.0)
Requires-Dist: pyshtools (>=4.0.0)
Requires-Dist: regionmask (>=0.13.0,<0.14.0)
Requires-Dist: scipy (>=1.0.0)
